{
  "root": "/Users/andrewlevin/Library/CloudStorage/OneDrive-СУНЦМГУШколаим.А.Н.Колмогорова,МГУим.М.В.Ломоносова/1 🏛 Biblioteka",
  "relative": "012 🏰 History/21 - Cambridge Collections. History/Кембриджская история древнего мира (Д.-М. Льюис Джон Бордмэн Дж.-К. Дэвис etc.).ddjvu compressed.pdf",
  "store": "../data/store",
  "type": "file",
  "id_short": "kembridz-244a208e",
  "id_long": "012 🏰 Hist🔹21 - Cambr🔹Кембриджск🔹244a208e",
  "cover": "kembridzhskaia-istoriia-drevnego-mira-d-m-liuis-dzhon-bordmen-dzh-k-devis-etc-ddjvu-compressed-pdf-244a208e.jpg"
}