{
  "root": "/Users/andrewlevin/Library/CloudStorage/OneDrive-СУНЦМГУШколаим.А.Н.Колмогорова,МГУим.М.В.Ломоносова/1 🏛 Biblioteka",
  "relative": "030 🪴 BioTech/Время генома. Как генетические технологии меняют наш мир и что это значит для нас (Липкин С.М. Луома Дж. (Lipkin S.M. etc.).pdf",
  "store": "../data/store",
  "type": "file",
  "id_short": "vremia-g-5e8aa5ed",
  "id_long": "030 🪴 BioT🔹Время гено🔹5e8aa5ed",
  "cover": "vremia-genoma-kak-geneticheskie-tekhnologii-meniaiut-nash-mir-i-chto-eto-znachit-dlia-nas-lipkin-s-m-luoma-dzh-lipkin-s-m-etc-pdf-5e8aa5ed.jpg"
}