{
  "root": "/Users/andrewlevin/Library/CloudStorage/OneDrive-СУНЦМГУШколаим.А.Н.Колмогорова,МГУим.М.В.Ломоносова/1 🏛 Biblioteka",
  "relative": "199 📬 Etc Books/Как информация управляет миром и определяет историю нашей Вселенной и живущих в ней видов (Идальго С.).pdf",
  "store": "../data/store",
  "type": "file",
  "id_short": "kak-info-104da1b2",
  "id_long": "199 📬 Etc 🔹Как информ🔹104da1b2",
  "cover": "kak-informatsiia-upravliaet-mirom-i-opredeliaet-istoriiu-nashei-vselennoi-i-zhivushchikh-v-nei-vidov-idalgo-s-pdf-104da1b2.jpg"
}