{
  "root": "/Users/andrewlevin/Library/CloudStorage/OneDrive-СУНЦМГУШколаим.А.Н.Колмогорова,МГУим.М.В.Ломоносова/1 🏛 Biblioteka",
  "relative": "199 📬 Etc Books/Точное мышление в безумные времена. Венский кружок и крестовый поход за основаниями науки (Карл Зигмунд).fb2",
  "store": "../data/store",
  "type": "file",
  "id_short": "tochnoe--51ddc9b2",
  "id_long": "199 📬 Etc 🔹Точное мыш🔹51ddc9b2"
}