{
  "root": "/Users/andrewlevin/Library/CloudStorage/OneDrive-СУНЦМГУШколаим.А.Н.Колмогорова,МГУим.М.В.Ломоносова/1 🏛 Biblioteka",
  "relative": "703 - Man-Ivanov-Farber - PUB/Стратегии которые р by Составители Карл Ште.pdf",
  "store": "../data/store",
  "type": "file",
  "id_short": "strategi-7feb3133",
  "id_long": "703 - Man-🔹Стратегии 🔹7feb3133",
  "cover": "strategii-kotorye-r-by-sostaviteli-karl-shte-pdf-7feb3133.jpg"
}