{
  "root": "/Users/andrewlevin/Library/CloudStorage/OneDrive-СУНЦМГУШколаим.А.Н.Колмогорова,МГУим.М.В.Ломоносова/1 🏛 Biblioteka",
  "relative": "705 - MCCMO Pub/Соровская олимпиада школьников Соста.ddjvu compressed.pdf",
  "store": "../data/store",
  "type": "file",
  "id_short": "sorovska-ac2941e2",
  "id_long": "705 - MCCM🔹Соровская 🔹ac2941e2",
  "cover": "sorovskaia-olimpiada-shkolnikov-sosta-ddjvu-compressed-pdf-ac2941e2.jpg"
}