{
  "root": "/Users/andrewlevin/Library/CloudStorage/OneDrive-СУНЦМГУШколаим.А.Н.Колмогорова,МГУим.М.В.Ломоносова/1 🏛 Biblioteka",
  "relative": "707 - Алетейя Pub/История европейской культуры Римская.pdf",
  "store": "../data/store",
  "type": "file",
  "id_short": "istoriia-7ee8ce65",
  "id_long": "707 - Алет🔹История ев🔹7ee8ce65",
  "cover": "istoriia-evropeiskoi-kultury-rimskaia-pdf-7ee8ce65.jpg"
}